Metadata-Version: 2.4
Name: pantheon-agents
Version: 0.3.2
Summary: A framework for building distributed evolvable multi-agent system.
Requires-Python: >=3.10
License-File: LICENSE
Requires-Dist: executor-engine>=0.3.3
Requires-Dist: fire>=0.7.0
Requires-Dist: funcdesc>=0.1.8
Requires-Dist: litellm>=1.56.4
Requires-Dist: loguru>=0.7.3
Requires-Dist: openai>=1.58.1
Requires-Dist: pillow>=10.4.0
Requires-Dist: rich>=13.9.4
Requires-Dist: rich-pyfiglet
Requires-Dist: ddgs>=9.5.2
Requires-Dist: pantheon-toolsets>=0.5.0
Requires-Dist: magique>=0.6.7
Provides-Extra: dev
Requires-Dist: pytest>=8.3.4; extra == "dev"
Requires-Dist: pytest-asyncio>=0.25.0; extra == "dev"
Provides-Extra: slack
Requires-Dist: slack-sdk; extra == "slack"
Requires-Dist: slack-bolt; extra == "slack"
Dynamic: license-file
